mpi_master_slave/__init__.py
mpi_master_slave/exceptions.py
mpi_master_slave/master_slave.py
mpi_master_slave/multi_work_queue.py
mpi_master_slave/test.py
mpi_master_slave/work_queue.py
mpi_master_slave-0.2.1.dist-info/METADATA
mpi_master_slave-0.2.1.dist-info/RECORD
mpi_master_slave-0.2.1.dist-info/WHEEL
mpi_master_slave-0.2.1.dist-info/top_level.txt
