Metadata-Version: 2.1
Name: mpi-master-slave
Version: 0.2.1
Summary: An MPI master-slave library for Python
Home-page: https://github.com/TerraFusion/mpi-master-slave
Author: luca-s
Author-email: luca.scarabello@gmail.com
License: UNKNOWN
Keywords: mpi,master,slave
Platform: UNKNOWN
Requires-Dist: mpi4py
